proteus/__init__.py
proteus/config.py
proteus/pyson.py
proteus/tests/__init__.py
proteus/tests/common.py
proteus/tests/test_action.py
proteus/tests/test_config.py
proteus/tests/test_context.py
proteus/tests/test_model.py
proteus/tests/test_readme.py
proteus/tests/test_report.py
proteus/tests/test_wizard.py
proteus-7.8.0.dist-info/licenses/LICENSE
proteus-7.8.0.dist-info/METADATA
proteus-7.8.0.dist-info/WHEEL
proteus-7.8.0.dist-info/top_level.txt
proteus-7.8.0.dist-info/zip-safe
proteus-7.8.0.dist-info/RECORD
